ytlv/__init__.py
ytlv/youtube_lv.py
youtube_lv-1.3.0.dist-info/LICENSE
youtube_lv-1.3.0.dist-info/METADATA
youtube_lv-1.3.0.dist-info/WHEEL
youtube_lv-1.3.0.dist-info/top_level.txt
youtube_lv-1.3.0.dist-info/RECORD
