Metadata-Version: 2.1
Name: youtube_lv
Version: 1.3.0
Summary: check youtuber live status
Home-page: https://github.com/phillychi3/youtube_lv
Author: phillychi3
Author-email: phillychi3@gmail.com
Classifier: Programming Language :: Python :: 3
Classifier: License :: OSI Approved :: Apache Software License
Classifier: Operating System :: OS Independent
License-File: LICENSE
Requires-Dist: requests
